{
  "type": "survivorsdelight:sd_cooking_pot",
  "container": {
    "count": 1,
    "id": "minecraft:bowl"
  },
  "cookingtime": 1200,
  "experience": 20.0,
  "fluid": {
    "tag": "c:milk"
  },
  "fluid_amount": 100,
  "ingredients": [
    {
      "type": "tfc:and",
      "children": [
        {
          "tag": "survivorsdelight:meats_for_shepherds_pie"
        },
        {
          "type": "tfc:not_rotten"
        }
      ]
    },
    {
      "type": "tfc:and",
      "children": [
        {
          "tag": "survivorsdelight:meats_for_shepherds_pie"
        },
        {
          "type": "tfc:not_rotten"
        }
      ]
    },
    {
      "type": "tfc:and",
      "children": [
        {
          "tag": "survivorsdelight:meats_for_shepherds_pie"
        },
        {
          "type": "tfc:not_rotten"
        }
      ]
    },
    {
      "type": "tfc:and",
      "children": [
        {
          "tag": "c:foods/dough"
        },
        {
          "type": "tfc:not_rotten"
        }
      ]
    },
    {
      "type": "tfc:and",
      "children": [
        {
          "item": "tfc:food/vegetables_salad"
        },
        {
          "type": "tfc:not_rotten"
        }
      ]
    }
  ],
  "result": {
    "count": 1,
    "id": "farmersdelight:shepherds_pie_block"
  }
}